<keymap version="1" name="Default copy" parent="$default">
  <action id="CloseContent">
    <keyboard-shortcut first-keystroke="ctrl f4" />
    <keyboard-shortcut first-keystroke="ctrl w" />
  </action>
  <action id="CloseProject">
    <keyboard-shortcut first-keystroke="shift ctrl alt back_space" />
  </action>
  <action id="Diff.ShowSettingsPopup" />
  <action id="EditorDeleteLine">
    <keyboard-shortcut first-keystroke="ctrl y" />
    <keyboard-shortcut first-keystroke="shift ctrl d" />
  </action>
  <action id="EditorSelectWord" />
  <action id="RecentProjectListGroup">
    <keyboard-shortcut first-keystroke="shift ctrl o" />
  </action>
</keymap>